{
    "abi-blacklist": [
        "stdcall",
        "fastcall",
        "vectorcall",
        "win64",
        "sysv64"
    ],
    "arch": "aarch64",
    "data-layout": "e-m:e-i8:8:32-i16:16:32-i64:64-i128:128-n32:64-S128",
    "env": "steed",
    "executables": true,
    "has-elf-tls": true,
    "linker": "ld.lld",
    "linker-flavor": "ld",
    "llvm-target": "aarch64-unknown-linux",
    "max-atomic-width": 128,
    "os": "linux",
    "panic-strategy": "abort",
    "pre-link-args": {
        "gcc": [
            "-Wl,--as-needed",
            "-Wl,-z,noexecstack",
            "-nostartfiles"
        ]
    },
    "target-c-int-width": "32",
    "target-endian": "little",
    "target-family": "unix",
    "target-pointer-width": "64",
    "vendor": "unknown"
}
